{
	"name": "CMS_Part_D_Raw_Delimited",
	"properties": {
		"linkedServiceName": {
			"referenceName": "synapsejrs-WorkspaceDefaultStorage",
			"type": "LinkedServiceReference"
		},
		"folder": {
			"name": "CMS"
		},
		"annotations": [],
		"type": "DelimitedText",
		"typeProperties": {
			"location": {
				"type": "AzureBlobFSLocation",
				"fileName": "PartD_Prescriber_PUF_NPI_Drug_13.txt",
				"folderPath": "cms-part-d/raw",
				"fileSystem": "synapselake"
			},
			"columnDelimiter": "\t",
			"escapeChar": "\\",
			"firstRowAsHeader": true,
			"quoteChar": "\""
		},
		"schema": [
			{
				"name": "npi",
				"type": "String"
			},
			{
				"name": "nppes_provider_last_org_name",
				"type": "String"
			},
			{
				"name": "nppes_provider_first_name",
				"type": "String"
			},
			{
				"name": "nppes_provider_city",
				"type": "String"
			},
			{
				"name": "nppes_provider_state",
				"type": "String"
			},
			{
				"name": "specialty_description",
				"type": "String"
			},
			{
				"name": "description_flag",
				"type": "String"
			},
			{
				"name": "drug_name",
				"type": "String"
			},
			{
				"name": "generic_name",
				"type": "String"
			},
			{
				"name": "bene_count",
				"type": "String"
			},
			{
				"name": "total_claim_count",
				"type": "String"
			},
			{
				"name": "total_30_day_fill_count",
				"type": "String"
			},
			{
				"name": "total_day_supply",
				"type": "String"
			},
			{
				"name": "total_drug_cost",
				"type": "String"
			},
			{
				"name": "bene_count_ge65",
				"type": "String"
			},
			{
				"name": "bene_count_ge65_suppress_flag",
				"type": "String"
			},
			{
				"name": "total_claim_count_ge65",
				"type": "String"
			},
			{
				"name": "ge65_suppress_flag",
				"type": "String"
			},
			{
				"name": "total_30_day_fill_count_ge65",
				"type": "String"
			},
			{
				"name": "total_day_supply_ge65",
				"type": "String"
			},
			{
				"name": "total_drug_cost_ge65",
				"type": "String"
			}
		]
	}
}