{
	"name": "trgNative",
	"properties": {
		"annotations": [],
		"runtimeState": "Started",
		"pipelines": [
			{
				"pipelineReference": {
					"referenceName": "Native_CMS_Part_D",
					"type": "PipelineReference"
				},
				"parameters": {
					"prmFile": "@triggerBody().fileName"
				}
			}
		],
		"type": "BlobEventsTrigger",
		"typeProperties": {
			"blobPathBeginsWith": "/synapselake/blobs/cms-part-d/raw/",
			"blobPathEndsWith": ".txt",
			"ignoreEmptyBlobs": true,
			"scope": "/subscriptions/201fa29b-5672-4347-9909-fa57d294b356/resourceGroups/synapsejrs/providers/Microsoft.Storage/storageAccounts/synapselakejrs",
			"events": [
				"Microsoft.Storage.BlobCreated"
			]
		}
	}
}